.travis.yml
LICENSE
MANIFEST.in
README.markdown
setup.cfg
setup.py
tox.ini
django_octopus.egg-info/PKG-INFO
django_octopus.egg-info/SOURCES.txt
django_octopus.egg-info/dependency_links.txt
django_octopus.egg-info/top_level.txt
octopus/__init__.py
octopus/apps.py
octopus/settings.py
octopus/views.py
octopus/static/__init__.py
octopus/static/octopus/custom-jquery.js
octopus/static/octopus/octopus.js
octopus/templates/octopus/ajax.html
octopus/templates/octopus/clear.html
octopus/templates/octopus/form.html
octopus/templates/octopus/link.html
octopus/templatetags/__init__.py
octopus/templatetags/tentacles.py
octopus/tools/__init__.py