Metadata-Version: 1.1
Name: django-octopus
Version: 0.4.1
Summary: A simple AJAX pull framework for django, now with fullfeatured demo
Home-page: https://github.com/brmc/django-octopus
Author: Brian McClure
Author-email: brian@mcclure.pw
License: MIT License
Download-URL: https://github.com/brmc/django-octopus.git
Keywords: django,ajax,front-end,pull
Platform: UNKNOWN
Classifier: Environment :: Web Environment
Classifier: Framework :: Django
Classifier: Intended Audience :: Developers
Classifier: Programming Language :: Python
Classifier: Programming Language :: Python :: 3.6
Requires: python (>= 3.6)
Requires: django (>= 1.8)
